gsalary_sdk/__init__.py
gsalary_sdk/client.py
gsalary_sdk/entities.py
gsalary_sdk-1.0.0.dist-info/licenses/LICENSE
gsalary_sdk-1.0.0.dist-info/METADATA
gsalary_sdk-1.0.0.dist-info/WHEEL
gsalary_sdk-1.0.0.dist-info/top_level.txt
gsalary_sdk-1.0.0.dist-info/RECORD
