Metadata-Version: 2.4
Name: gsalary_sdk
Version: 1.0.0
Summary: GSalary SDK for Python
Home-page: https://github.com/gsalary-develop/gsalary-sdk-python
Author: Astro
Author-email: Astro <astro.dai@globalfreepay.com>
License-Expression: MIT
Project-URL: Homepage, https://github.com/gsalary-develop/gsalary-sdk-python
Project-URL: Issues, https://github.com/gsalary-develop/gsalary-sdk-python/issues
Classifier: Programming Language :: Python :: 3
Classifier: Operating System :: OS Independent
Requires-Python: >=3.7
License-File: LICENSE
Requires-Dist: cryptography
Dynamic: author
Dynamic: home-page
Dynamic: license-file
